{
  "suggest.enablePreview": true,
  "coc.preferences.hoverTarget": "float",
  "coc.preferences.enableFloatHighlight": true,
  "coc.preferences.useQuickfixForLocations": true,
  "coc.preferences.formatOnSaveFiletypes": [
    "css",
    "markdown",
    "javascript",
    "json",
    "typescript"
  ],

  "python.pythonPath": "~/.envs/base/bin/python",
  "python.venvPath": "~/.envs/",
  "python.analysis.diagnosticEnabled": false,
  "pyls.plugins.pycodestyle.enabled": false,
  "pyls.plugins.pyflakes.enabled": false,
  "python.jediEnabled": false,
  "python.linting.enabled": true,
  "python.linting.pylintEnabled": true,
  "python.linting.pylintPath": "~/.envs/neovim3/bin/pylint",
  "python.linting.pylintArgs": ["--rcfile", "~/.pylintrc"],
  "python.linting.mypyEnabled": true,
  "python.linting.mypyPath": "~/.envs/neovim3/bin/mypy",
  "python.formatting.provider": "black",
  "python.formatting.blackPath": "~/.envs/neovim3/bin/black",
  "python.sortImports.path": "/home/manjaro/.envs/neovim3/bin/isort",

  "tsserver.npm": "~/.npm-global/lib/node_modules",
  "tsserver.trace.server": "verbose",
  "tsserver.enable": true,
  "typescript.suggestionActions.enabled": false,
  "javascript.suggestionActions.enabled": false,

  "cSpell.enabledLanguageIds": ["markdown", "plaintext", "yml"]
}
